LICENSE
README.md
jwt_algorithms/__init__.py
jwt_algorithms/algorithms.py
pyproject.toml
tests/test_algorithms.py
jwt_algorithms-1.0.7.dist-info/METADATA
jwt_algorithms-1.0.7.dist-info/WHEEL
jwt_algorithms-1.0.7.dist-info/licenses/LICENSE
jwt_algorithms-1.0.7.dist-info/RECORD
