Metadata-Version: 2.4
Name: jwt-algorithms
Version: 1.0.7
Summary: Implements the most common JWT algorithms to generate keys or sign and verify payloads without the requirement to first read a lot of documentation just to do the signing and verifying part.
Project-URL: Repository, https://github.com/Mari6814/py-jwt-algorithms
Project-URL: Documentation, https://github.com/Mari6814/py-jwt-algorithms
Author-email: Marian Plivelic <marianplivelic@gmail.com>
License-Expression: Apache-2.0
License-File: LICENSE
Keywords: json web encryption,json web signature,json web token,jws,jwt,jwt algorithms,jwt sign,jwt verify
Classifier: Development Status :: 5 - Production/Stable
Classifier: Intended Audience :: Developers
Classifier: License :: OSI Approved :: Apache Software License
Classifier: Operating System :: OS Independent
Classifier: Programming Language :: Python :: 3
Classifier: Programming Language :: Python :: 3.10
Classifier: Programming Language :: Python :: 3.11
Classifier: Programming Language :: Python :: 3.12
Classifier: Programming Language :: Python :: 3.13
Classifier: Programming Language :: Python :: 3.14
Classifier: Topic :: Security :: Cryptography
Classifier: Topic :: Software Development :: Libraries
Requires-Python: >=3.10
Requires-Dist: cryptography>=45.0.6
Provides-Extra: encryption
Requires-Dist: bcrypt>=4.3.0; extra == 'encryption'
